gllm_retrieval/__init__.pyi
gllm_retrieval/chunk_processor/__init__.pyi
gllm_retrieval/chunk_processor/chunk_processor.pyi
gllm_retrieval/chunk_processor/dedupe_chunk_processor.pyi
gllm_retrieval/chunk_processor/merging_chunk_processor.pyi
gllm_retrieval/constants.pyi
gllm_retrieval/query_transformer/__init__.pyi
gllm_retrieval/query_transformer/many_to_one_query_transformer.pyi
gllm_retrieval/query_transformer/no_op_query_transformer.pyi
gllm_retrieval/query_transformer/one_to_many_query_transformer.pyi
gllm_retrieval/query_transformer/one_to_one_query_transformer.pyi
gllm_retrieval/query_transformer/query_transformer.pyi
gllm_retrieval/query_transformer/text_to_sql_query_transformer.pyi
gllm_retrieval/reranker/__init__.pyi
gllm_retrieval/reranker/flag_embedding_reranker.pyi
gllm_retrieval/reranker/reranker.pyi
gllm_retrieval/reranker/similarity_based_reranker.pyi
gllm_retrieval/retrieval_parameter_extractor/__init__.pyi
gllm_retrieval/retrieval_parameter_extractor/lm_based_retrieval_parameter_extractor.pyi
gllm_retrieval/retrieval_parameter_extractor/retrieval_parameter_extractor.pyi
gllm_retrieval/retrieval_parameter_extractor/validator/__init__.pyi
gllm_retrieval/retrieval_parameter_extractor/validator/default_json_rules.pyi
gllm_retrieval/retrieval_parameter_extractor/validator/default_pydantic_rules.pyi
gllm_retrieval/retriever/__init__.pyi
gllm_retrieval/retriever/graph_retriever/__init__.pyi
gllm_retrieval/retriever/graph_retriever/graph_rag_retriever.pyi
gllm_retrieval/retriever/graph_retriever/llama_index_graph_rag_retriever.pyi
gllm_retrieval/retriever/graph_retriever/util.pyi
gllm_retrieval/retriever/sql_retriever/__init__.pyi
gllm_retrieval/retriever/sql_retriever/basic_sql_retriever.pyi
gllm_retrieval/retriever/sql_retriever/sql_retriever.pyi
gllm_retrieval/retriever/vector_retriever/__init__.pyi
gllm_retrieval/retriever/vector_retriever/basic_vector_retriever.pyi
gllm_retrieval/retriever/vector_retriever/vector_retriever.pyi
gllm_retrieval_binary-0.3.2.dist-info/METADATA
gllm_retrieval_binary-0.3.2.dist-info/WHEEL
gllm_retrieval_binary-0.3.2.dist-info/RECORD
