Metadata-Version: 2.1
Name: gllm-retrieval-binary
Version: 0.3.2
Summary: A library containing retrieval related components in Gen AI applications.
Author: Dimitrij Ray
Author-email: dimitrij.ray@gdplabs.id
Requires-Python: >=3.11,<3.13
Classifier: Programming Language :: Python :: 3
Classifier: Programming Language :: Python :: 3.11
Classifier: Programming Language :: Python :: 3.12
Provides-Extra: elasticsearch
Provides-Extra: flag-embedding
Provides-Extra: kg
Provides-Extra: sql
Provides-Extra: torch
Requires-Dist: FlagEmbedding (>=1.2.5,<2.0.0) ; extra == "flag-embedding"
Requires-Dist: gllm-core-binary
Requires-Dist: gllm-datastore-binary[kg] ; extra == "kg"
Requires-Dist: gllm-inference-binary
Requires-Dist: jsonschema (>=4.21.1,<5.0.0)
Requires-Dist: langchain (>=0.3.0,<0.4.0)
Requires-Dist: langchain-community (==0.3.0)
Requires-Dist: langchain-core (>=0.3.0,<0.4.0)
Requires-Dist: langchain-elasticsearch (==0.3.0) ; extra == "elasticsearch"
Requires-Dist: libmagic (>=1.0,<2.0) ; sys_platform == "win32"
Requires-Dist: llama-index-core (>=0.12.0,<0.13.0)
Requires-Dist: llama-index-embeddings-openai (>=0.3.0,<0.4.0) ; extra == "kg"
Requires-Dist: llama-index-llms-openai (>=0.3.0,<0.4.0) ; extra == "kg"
Requires-Dist: numpy (>=1.26.4,<2.0.0) ; extra == "flag-embedding"
Requires-Dist: peft (>=0.12.0,<0.13.0) ; extra == "flag-embedding"
Requires-Dist: python-magic-bin (>=0.4.14,<0.5.0) ; sys_platform == "win32"
Requires-Dist: sqlglot (>=26.3.9,<27.0.0) ; extra == "sql"
Requires-Dist: torch (>=2.2.0,<2.3.0) ; extra == "flag-embedding" or extra == "torch"
